{"cameraMode":{"drawMode":0,"name":"Shaded","section":"Shading Mode"},"sceneLighting":true,"audioPlay":false,"sceneViewState":{"m_AlwaysRefresh":false,"showFog":true,"showSkybox":true,"showFlares":true,"showImageEffects":true,"showParticleSystems":true,"showVisualEffectGraphs":true,"m_FxEnabled":true},"in2DMode":false,"pivot":{"x":3.6478970050811769,"y":-0.9825698733329773,"z":-2.537259817123413},"rotation":{"x":0.2029363065958023,"y":0.6405940055847168,"z":-0.18102610111236573,"w":0.7181264758110046},"size":15.607866287231446,"orthographic":false}